cb_gwi_gpp/__init__.py
cb_gwi_gpp/cb_gwi_gpp.py
examples/example0.py
cb_gwi_gpp-0.1.0.dev4.dist-info/METADATA
cb_gwi_gpp-0.1.0.dev4.dist-info/WHEEL
cb_gwi_gpp-0.1.0.dev4.dist-info/entry_points.txt
cb_gwi_gpp-0.1.0.dev4.dist-info/RECORD
