Metadata-Version: 2.4
Name: cb_gwi_gpp
Version: 0.1.0.dev4
Project-URL: Homepage, https://github.com/chriesibaum/cb_gwi_gpp
Requires-Python: >=3.12
Requires-Dist: cb-pyutils
Requires-Dist: key-stroke
Requires-Dist: pyserial
Requires-Dist: pyvisa
Requires-Dist: pyvisa-py
